yamlemxconvert/__init__.py
yamlemxconvert/__version__.py
yamlemxconvert/convert.py
yamlemxconvert/convert2.py
yamlemxconvert/emxWriter.py
yamlemxconvert/mappings.py
yamlemxconvert/markdownWriter.py
yamlemxconvert/utils.py
yamlemxconvert-1.3.0.dist-info/LICENSE
yamlemxconvert-1.3.0.dist-info/METADATA
yamlemxconvert-1.3.0.dist-info/WHEEL
yamlemxconvert-1.3.0.dist-info/top_level.txt
yamlemxconvert-1.3.0.dist-info/RECORD
