Metadata-Version: 2.1
Name: yamlemxconvert
Version: 1.3.0
Summary: Write and build EMX data models in YAML format
Home-page: https://github.com/davidruvolo51/yaml-emx-convert
Author: David Ruvolo
Author-email: d.c.ruvolo@gmail.com
License: MIT
Classifier: License :: OSI Approved :: MIT License
Classifier: Programming Language :: Python
Classifier: Programming Language :: Python :: 3
Classifier: Programming Language :: Python :: 3.6
Classifier: Programming Language :: Python :: Implementation :: CPython
Classifier: Programming Language :: Python :: Implementation :: PyPy
Classifier: Intended Audience :: Science/Research
Requires-Python: >=3.6.0
License-File: LICENSE
Requires-Dist: PyYAML
Requires-Dist: pandas
